{
    "Canon": [{
        "name": "Canon PowerShot G10",
        "label": "PowerShot G10"
    }, {
        "name": "G11",
        "label": "PowerShot G11"
    }, {
        "name": "550D",
        "Label": "EOS 550D"
    }],
    "Nikon": [{
        "name": "D90",
        "label": "D90"
    }, {
        "name": "D300",
        "label": "D300"
    }, {
        "name": "D3S",
        "label": "D3S"
    }],
    "Sony": [{
        "name": "DSLR-A500",
        "label": "α500"
    }, {
        "name": "DSLR-A290",
        "label": "α290"
    }, {
        "name": "NEX-5",
        "label": "NEX-5"
    }]
}
